loopsage/__init__.py
loopsage/args_definition.py
loopsage/em.py
loopsage/initial_structures.py
loopsage/knots.py
loopsage/md.py
loopsage/plots.py
loopsage/preproc.py
loopsage/run.py
loopsage/stochastic_simulation.py
loopsage/utils.py
loopsage/vizualization_tools.py
loopsage/forcefields/classic_sm_ff.xml
pyloopsage-1.1.5.dist-info/licenses/LICENSE
pyloopsage-1.1.5.dist-info/METADATA
pyloopsage-1.1.5.dist-info/WHEEL
pyloopsage-1.1.5.dist-info/entry_points.txt
pyloopsage-1.1.5.dist-info/top_level.txt
pyloopsage-1.1.5.dist-info/RECORD
