Metadata-Version: 2.4
Name: pyLoopSage
Version: 1.1.5
Summary: An energy-based stochastic model of loop extrusion in chromatin.
Home-page: https://github.com/SFGLab/pyLoopSage
Author: Sebastian Korsak
Author-email: s.korsak@datascience.edu.pl
License: GNU General Public License v3.0
Classifier: Programming Language :: Python :: 3
Classifier: License :: OSI Approved :: GNU General Public License v3 (GPLv3)
Classifier: Operating System :: POSIX :: Linux
Requires-Python: >=3.10
License-File: LICENSE
Requires-Dist: numpy<2.0,>1.2
Requires-Dist: numba
Requires-Dist: scipy
Requires-Dist: pandas
Requires-Dist: argparse
Requires-Dist: matplotlib
Requires-Dist: mdtraj
Requires-Dist: seaborn
Requires-Dist: scikit-learn
Requires-Dist: configparser
Requires-Dist: typing-extensions
Requires-Dist: tqdm
Requires-Dist: pyvista[all]
Requires-Dist: OpenMM
Requires-Dist: OpenMM-cuda
Requires-Dist: statsmodels
Requires-Dist: imageio
Requires-Dist: imageio[ffmpeg]
Requires-Dist: pillow
Requires-Dist: pyBigWig
Requires-Dist: topoly
Dynamic: author
Dynamic: author-email
Dynamic: classifier
Dynamic: description
Dynamic: description-content-type
Dynamic: home-page
Dynamic: license
Dynamic: license-file
Dynamic: requires-dist
Dynamic: requires-python
Dynamic: summary
